[{"StationID":"1020","StationName":{"Zh_tw":"板橋","En":"Banqiao"},"TrainNo":"442","Direction":0,"TrainTypeID":"110G","TrainTypeCode":"11","TrainTypeName":{"Zh_tw":"自強(3000)(EMU3000 型電車)","En":"Tze-Chiang Ltd. Express(3000)"},"TripLine":0,"EndingStationID":"6000","EndingStationName":{"Zh_tw":"臺東","En":"Taitung"},"ScheduledArrivalTime":"16:45:00","ScheduledDepartureTime":"16:47:00","DelayTime":0,"SrcUpdateTime":"2024-11-28T16:44:23+08:00","UpdateTime":"2024-11-28T16:45:21+08:00"},{"StationID":"1020","StationName":{"Zh_tw":"板橋","En":"Banqiao"},"TrainNo":"273","Direction":1,"TrainTypeID":"1107","TrainTypeCode":"2","TrainTypeName":{"Zh_tw":"普悠瑪(普悠瑪)","En":"Puyuma Express"},"TripLine":1,"EndingStationID":"3360","EndingStationName":{"Zh_tw":"彰化","En":"Changhua"},"ScheduledArrivalTime":"16:47:00","ScheduledDepartureTime":"16:48:00","DelayTime":0,"SrcUpdateTime":"2024-11-28T16:43:33+08:00","UpdateTime":"2024-11-28T16:45:21+08:00"},{"StationID":"1020","StationName":{"Zh_tw":"板橋","En":"Banqiao"},"TrainNo":"122","Direction":0,"TrainTypeID":"1109","TrainTypeCode":"3","TrainTypeName":{"Zh_tw":"自強(推拉式自強號且無自行車車廂)","En":"Tze-Chiang Limited Express"},"TripLine":1,"EndingStationID":"0900","EndingStationName":{"Zh_tw":"基隆","En":"Keelung"},"ScheduledArrivalTime":"16:49:00","ScheduledDepartureTime":"16:51:00","DelayTime":3,"SrcUpdateTime":"2024-11-28T16:44:27+08:00","UpdateTime":"2024-11-28T16:45:21+08:00"},{"StationID":"1020","StationName":{"Zh_tw":"板橋","En":"Banqiao"},"TrainNo":"1221","Direction":1,"TrainTypeID":"1131","TrainTypeCode":"6","TrainTypeName":{"Zh_tw":"區間","En":"Local Train"},"TripLine":0,"EndingStationID":"1210","EndingStationName":{"Zh_tw":"新竹","En":"Hsinchu"},"ScheduledArrivalTime":"16:54:00","ScheduledDepartureTime":"16:55:00","DelayTime":0,"SrcUpdateTime":"2024-11-28T16:42:31+08:00","UpdateTime":"2024-11-28T16:45:21+08:00"},{"StationID":"1020","StationName":{"Zh_tw":"板橋","En":"Banqiao"},"TrainNo":"1222","Direction":0,"TrainTypeID":"1131","TrainTypeCode":"6","TrainTypeName":{"Zh_tw":"區間","En":"Local Train"},"TripLine":0,"EndingStationID":"0900","EndingStationName":{"Zh_tw":"基隆","En":"Keelung"},"ScheduledArrivalTime":"17:01:00","ScheduledDepartureTime":"17:02:00","DelayTime":6,"SrcUpdateTime":"2024-11-28T16:40:27+08:00","UpdateTime":"2024-11-28T16:45:21+08:00"},{"StationID":"1020","StationName":{"Zh_tw":"板橋","En":"Banqiao"},"TrainNo":"516","Direction":0,"TrainTypeID":"1110","TrainTypeCode":"4","TrainTypeName":{"Zh_tw":"莒光(無身障座位)","En":"Chu-Kuang Express"},"TripLine":2,"EndingStationID":"0930","EndingStationName":{"Zh_tw":"七堵","En":"Qidu"},"ScheduledArrivalTime":"17:05:00","ScheduledDepartureTime":"17:07:00","DelayTime":4,"SrcUpdateTime":"2024-11-28T16:42:55+08:00","UpdateTime":"2024-11-28T16:45:21+08:00"},{"StationID":"1020","StationName":{"Zh_tw":"板橋","En":"Banqiao"},"TrainNo":"139","Direction":1,"TrainTypeID":"1108","TrainTypeCode":"3","TrainTypeName":{"Zh_tw":"自強(推拉式自強號且無自行車車廂)","En":"Tze-Chiang Limited Express"},"TripLine":1,"EndingStationID":"5050","EndingStationName":{"Zh_tw":"潮州","En":"Chaozhou"},"ScheduledArrivalTime":"17:08:00","ScheduledDepartureTime":"17:10:00","DelayTime":0,"SrcUpdateTime":"2024-11-28T16:42:23+08:00","UpdateTime":"2024-11-28T16:45:21+08:00"},{"StationID":"1020","StationName":{"Zh_tw":"板橋","En":"Banqiao"},"TrainNo":"1223","Direction":1,"TrainTypeID":"1131","TrainTypeCode":"6","TrainTypeName":{"Zh_tw":"區間","En":"Local Train"},"TripLine":0,"EndingStationID":"1210","EndingStationName":{"Zh_tw":"新竹","En":"Hsinchu"},"ScheduledArrivalTime":"17:13:00","ScheduledDepartureTime":"17:14:00","DelayTime":0,"SrcUpdateTime":"2024-11-28T16:41:51+08:00","UpdateTime":"2024-11-28T16:45:21+08:00"}]